solution_efe_config/__init__.py
solution_efe_config/configConstants.py
solution_efe_config/configService.py
solution_efe_config-1.0.0.dist-info/METADATA
solution_efe_config-1.0.0.dist-info/WHEEL
solution_efe_config-1.0.0.dist-info/top_level.txt
solution_efe_config-1.0.0.dist-info/RECORD
